cr/__init__.py
cr/ai_layer.py
cr/bitbucket.py
cr/cli.py
your_code_reviewer-0.1.0.dist-info/METADATA
your_code_reviewer-0.1.0.dist-info/WHEEL
your_code_reviewer-0.1.0.dist-info/entry_points.txt
your_code_reviewer-0.1.0.dist-info/top_level.txt
your_code_reviewer-0.1.0.dist-info/RECORD
