Metadata-Version: 2.1
Name: your-code-reviewer
Version: 0.1.0
Requires-Dist: requests
Requires-Dist: python-dotenv
Requires-Dist: groq
